{"name":"Por Coruña for the Nokia N9","tagline":"Public transportation application for the Nokia N9 for the city of A Coruña","body":"Por Coru&ntilde;a for the Nokia N9\r\n===========================\r\n\r\nWhat is it?\r\n-----------\r\n\r\nPor Coru&ntilde;a is a public transportation application for the [Nokia N9][0]. It\r\ncurrently provides information about [A Coru&ntilde;a][1]'s bus lines, bus stops\r\nand bus arrival times, allowing users to save their favorite bus stops.\r\n\r\nHow does it work?\r\n-----------------\r\n\r\nPor Coru&ntilde;a is happily using [M&oacute;vete][2]'s API. [M&oacute;vete][2] has been\r\ndeveloped by [V&iacute;ctor Pena][3], who has also provided an iOS\r\nimplementation, already available in the [App Store][4].\r\n\r\nBugs & Feedback\r\n---------------\r\n\r\nPor Coru&ntilde;a has been developed with the hope of being useful, but for sure\r\nthings can be improved. If you find bugs or have any ideas to make it\r\nbetter, don't hesitate to create an entry in our [bug tracker][5].\r\n\r\nScreenshots\r\n-----------\r\n\r\n[Main View][6], [Search View][7], [Line View][8], [Stop View][9]\r\n\r\nLicense\r\n-------\r\n\r\nPor Coru&ntilde;a is free software: you can redistribute it and/or modify it under\r\nthe terms of the GNU General Public License as published by the Free\r\nSoftware Foundation, either version 3 of the License, or (at your option)\r\nany later version.\r\n\r\n[0]: http://swipe.nokia.com/ \"Nokia N9\"\r\n[1]: http://en.wikipedia.org/wiki/A_Coru%C3%B1a \"A Coru&ntilde;a\"\r\n[2]: http://movete.trabesoluciones.net/ \"M&oacute;vete\"\r\n[3]: http://www.victorpena.es/ \"V&iacute;ctor Pena\"\r\n[4]: http://ir.gl/movete \"M&oacute;vete for iOS\"\r\n[5]: https://github.com/spenap/porcorunha/issues \"Bug Tracker\"\r\n[6]: http://www.flickr.com/photos/bulfaiter/6902651496/\r\n[7]: http://www.flickr.com/photos/bulfaiter/6902651584/\r\n[8]: http://www.flickr.com/photos/bulfaiter/7048742579/\r\n[9]: http://www.flickr.com/photos/bulfaiter/6902651702/","google":"","note":"Don't delete this file! It's used internally to help with page regeneration."}